Metadata-Version: 2.1
Name: PathMePy
Version: 0.5.3
Summary: A tool to add scripts to Path
Author: Gustoon
Author-email: 
Classifier: Programming Language :: Python :: 3
Classifier: License :: OSI Approved :: MIT License
Classifier: Operating System :: OS Independent
Requires-Python: >=3.2
